README.md
setup.py
src/micro_py/__init__.py
src/micro_py/micro.py
src/micro_py/options.py
src/micro_py.egg-info/PKG-INFO
src/micro_py.egg-info/SOURCES.txt
src/micro_py.egg-info/dependency_links.txt
src/micro_py.egg-info/requires.txt
src/micro_py.egg-info/top_level.txt
src/micro_py/registry/__init__.py
src/micro_py/registry/consul.py