Metadata-Version: 1.0
Name: micro-py
Version: 1.0.7
Summary: python micro tool
Home-page: https://github.com/yylany/py-micro.git
Author: yyl
Author-email: 1906600192@qq.com
License: UNKNOWN
Platform: UNKNOWN
